bioinfolearn/__init__.py
bioinfolearn/dnatoolkit.py
bioinfolearn/main.py
bioinfolearn/pattern.py
bioinfolearn/structure.py
bioinfolearn/utils.py
bioinfolearn/version.py
bioinfolearn-0.1.dist-info/METADATA
bioinfolearn-0.1.dist-info/WHEEL
bioinfolearn-0.1.dist-info/top_level.txt
bioinfolearn-0.1.dist-info/RECORD
